fenix_library_running-0.0.10-py3.9-nspkg.pth
fenix_library/running/__init__.py
fenix_library/running/running.py
fenix_library_running-0.0.10.dist-info/LICENSE
fenix_library_running-0.0.10.dist-info/METADATA
fenix_library_running-0.0.10.dist-info/WHEEL
fenix_library_running-0.0.10.dist-info/namespace_packages.txt
fenix_library_running-0.0.10.dist-info/top_level.txt
fenix_library_running-0.0.10.dist-info/RECORD
